LoRa/LoRa.py
LoRa/__init__.py
LoRa/constants.py
LoRa/my_types.py
LoRa/boards/__init__.py
LoRa/boards/board.py
LoRa/boards/board_model_b.py
LoRa/boards/board_pico.py
LoRa/boards/board_rpi_w.py
LoRa/boards/board_zero.py
console/Ansi.py
console/__init__.py
forge/__init__.py
Strawberry_PI-0.0.110.dist-info/METADATA
Strawberry_PI-0.0.110.dist-info/WHEEL
Strawberry_PI-0.0.110.dist-info/entry_points.txt
Strawberry_PI-0.0.110.dist-info/top_level.txt
Strawberry_PI-0.0.110.dist-info/RECORD
